django_optimize_image-0.3.0.dist-info/licenses/LICENSE
optimizer_middleware/__init__.py
optimizer_middleware/middleware.py
optimizer_middleware/utils.py
tests/__init__.py
tests/settings.py
tests/test_middleware.py
django_optimize_image-0.3.0.dist-info/METADATA
django_optimize_image-0.3.0.dist-info/WHEEL
django_optimize_image-0.3.0.dist-info/top_level.txt
django_optimize_image-0.3.0.dist-info/RECORD
