Metadata-Version: 2.4
Name: django-optimize-image
Version: 0.3.0
Summary: A Django middleware to optimize image uploads by converting them to WebP.
Home-page: https://github.com/nahom-d54/django-optimize-image
Author: Nahom D
Author-email: nahom@nahom.eu.org
License-File: LICENSE
Requires-Dist: Pillow
Requires-Dist: Django
Provides-Extra: django32
Requires-Dist: Django<4.0,>=3.2; extra == "django32"
Provides-Extra: django42
Requires-Dist: Django<5.0,>=4.2; extra == "django42"
Provides-Extra: django50
Requires-Dist: Django<6.0,>=5.0; extra == "django50"
Dynamic: author
Dynamic: author-email
Dynamic: description
Dynamic: description-content-type
Dynamic: home-page
Dynamic: license-file
Dynamic: requires-dist
Dynamic: summary
